fifo_pj/fifo_project/fifo.sv
// Simple synchronous FIFO (single clock)

module fifo #(
    parameter int DATA_WIDTH = 8,
    parameter int DEPTH      = 8
) (
    input  logic                     clk,
    input  logic                     rst,       // async high reset (synced inside)
    input  logic                     write_en,
    input  logic                     read_en,
    input  logic [DATA_WIDTH-1:0]    data_in,
    output logic [DATA_WIDTH-1:0]    data_out,
    output logic                     full,
    output logic                     empty
);

    localparam int PTR_W   = (DEPTH <= 2) ? 1 : $clog2(DEPTH);
    localparam int COUNT_W = $clog2(DEPTH+1);

    //Purpose
    //PTR_W decides how many bits are needed for the read pointer(rd_ptr)
    //and write pointer to index the fifo memory.
    //
    logic [DATA_WIDTH-1:0] mem [0:DEPTH-1];
    logic [PTR_W-1:0]      wr_ptr, rd_ptr;
    logic [COUNT_W-1:0]    count;

    // status (size the RHS to LHS width to avoid WIDTHEXPAND)
    assign full  = (count == COUNT_W'(DEPTH));
    assign empty = (count == '0);

    // write/read
    always_ff @(posedge clk or posedge rst) begin
        if (rst) begin
            wr_ptr   <= '0;
            rd_ptr   <= '0;
            count    <= '0;
            data_out <= '0;
        end else begin
            // write path
            if (write_en && !full) begin
                mem[wr_ptr] <= data_in;
                wr_ptr <= (wr_ptr == PTR_W'(DEPTH-1)) ? '0 : (wr_ptr + 1'b1);
                count  <= count + 1'b1;
            end
            // read path
            if (read_en && !empty) begin
                data_out <= mem[rd_ptr];
                rd_ptr <= (rd_ptr == PTR_W'(DEPTH-1)) ? '0 : (rd_ptr + 1'b1);
                count  <= count - 1'b1;
            end
        end
    end

endmodule
'q!

fifo_pj/fifo_project/sim.vcd
$version Generated by VerilatedVcd $end
$timescale 1ps $end
 $scope module TOP $end
  $var wire 1 . clk $end
  $var wire 1 / rst $end
  $var wire 1 0 write_en $end
  $var wire 1 1 read_en $end
  $var wire 8 2 data_in [7:0] $end
  $var wire 8 3 data_out [7:0] $end
  $var wire 1 4 full $end
  $var wire 1 5 empty $end
  $scope module fifo $end
   $var wire 32 6 DATA_WIDTH [31:0] $end
   $var wire 32 6 DEPTH [31:0] $end
   $var wire 1 . clk $end
   $var wire 1 / rst $end
   $var wire 1 0 write_en $end
   $var wire 1 1 read_en $end
   $var wire 8 2 data_in [7:0] $end
   $var wire 8 3 data_out [7:0] $end
   $var wire 1 4 full $end
   $var wire 1 5 empty $end
   $var wire 32 7 PTR_W [31:0] $end
   $var wire 32 8 COUNT_W [31:0] $end
   $var wire 8 # mem[0] [7:0] $end
   $var wire 8 $ mem[1] [7:0] $end
   $var wire 8 % mem[2] [7:0] $end
   $var wire 8 & mem[3] [7:0] $end
   $var wire 8 ' mem[4] [7:0] $end
   $var wire 8 ( mem[5] [7:0] $end
   $var wire 8 ) mem[6] [7:0] $end
   $var wire 8 * mem[7] [7:0] $end
   $var wire 3 + wr_ptr [2:0] $end
   $var wire 3 , rd_ptr [2:0] $end
   $var wire 4 - count [3:0] $end
  $upscope $end
 $upscope $end
$enddefinitions $end


#0
b00000000 #
b00000000 $
b00000000 %
b00000000 &
b00000000 '
b00000000 (
b00000000 )
b00000000 *
b000 +
b000 ,
b0000 -
0.
1/
00
01
b00000000 2
b00000000 3
04
15
b00000000000000000000000000001000 6
b00000000000000000000000000000011 7
b00000000000000000000000000000100 8
#1
1.
#2
0.
#3
1.
#4
0.
0/
10
#5
b001 +
b0001 -
1.
05
#6
0.
b00000001 2
#7
b00000001 $
b010 +
b0010 -
1.
#8
0.
b00000010 2
#9
b00000010 %
b011 +
b0011 -
1.
#10
0.
b00000011 2
#11
b00000011 &
b100 +
b0100 -
1.
#12
0.
b00000100 2
#13
b00000100 '
b101 +
b0101 -
1.
#14
0.
b00000101 2
#15
b00000101 (
b110 +
b0110 -
1.
#16
0.
b00000110 2
#17
b00000110 )
b111 +
b0111 -
1.
#18
0.
b00000111 2
#19
b00000111 *
b000 +
b1000 -
1.
14
#20
0.
b01100011 2
#21
1.
#22
0.
00
11
#23
b001 ,
b0111 -
1.
04
#24
0.
#25
b010 ,
b0110 -
1.
b00000001 3
#26
0.
#27
b011 ,
b0101 -
1.
b00000010 3
#28
0.
#29
b100 ,
b0100 -
1.
b00000011 3
#30
0.
#31
b101 ,
b0011 -
1.
b00000100 3
#32
0.
#33
b110 ,
b0010 -
1.
b00000101 3
#34
0.
#35
b111 ,
b0001 -
1.
b00000110 3
#36
0.
#37
b000 ,
b0000 -
1.
b00000111 3
15
