gtkwave_test/counter.sv
module counter (
    input logic clk,
    input logic rst,
    output logic [3:0] count
);
    always_ff @(posedge clk or posedge rst) begin
        if (rst)
            count <= 0;
        else
            count <= count + 1;
    end
endmodule

gtkwave_test/wave.vcd
$version Generated by VerilatedVcd $end
$timescale 1ps $end
 $scope module TOP $end
  $var wire 1 # clk $end
  $var wire 1 $ rst $end
  $var wire 4 % count [3:0] $end
  $scope module counter $end
   $var wire 1 # clk $end
   $var wire 1 $ rst $end
   $var wire 4 % count [3:0] $end
  $upscope $end
 $upscope $end
$enddefinitions $end


#0
1#
1$
b0000 %
#10
0#
#20
1#
0$
b0001 %
#30
0#
#40
1#
b0010 %
#50
0#
#60
1#
b0011 %
#70
0#
#80
1#
b0100 %
#90
0#
#100
1#
b0101 %
#110
0#
#120
1#
b0110 %
#130
0#
#140
1#
b0111 %
#150
0#
#160
1#
b1000 %
#170
0#
#180
1#
b1001 %
